keras_eo/__init__.py
keras_eo/hello.py
keras_eo-2023.7.14.post2.dist-info/WHEEL
keras_eo-2023.7.14.post2.dist-info/METADATA
keras_eo-2023.7.14.post2.dist-info/RECORD
