Metadata-Version: 2.1
Name: keras-eo
Version: 2023.7.14.post2
Summary: Deep Learning for Earth Observation with Keras
Author: Juan Sensio
Author-email: it@earthpulse.es
Requires-Python: >=3.8,<4.0
Classifier: Programming Language :: Python :: 3
Classifier: Programming Language :: Python :: 3.8
Classifier: Programming Language :: Python :: 3.9
Classifier: Programming Language :: Python :: 3.10
Classifier: Programming Language :: Python :: 3.11
